{
  "updated": "2025-10-05T21:20:34.451909",
  "trends": [
    {
      "rank": 1,
      "query": "juventus – ac milán",
      "news_title": "Italské titulky: Génius, který bere dech",
      "news_url": "https://sempremilan.com/front-pages-italy-5-october-juventus-milan",
      "picture": "https://encrypted-tbn2.gstatic.com/images?q=tbn:ANd9GcRFhJ11MGnWjOPfDWg3C0JxGMnvEUoocZT-mOWmnzhGvuxzdWuigiYXjokBwHI",
      "traffic": "500++ hledání",
      "source": "SempreMilan",
      "explore_url": "https://trends.google.cz/trends/explore?q=juventus – ac milán&geo=CZ"
    },
    {
      "rank": 2,
      "query": "ratolesti serial",
      "news_title": "Recenze: Seriál Ratolesti řeší problémy ze střední",
      "news_url": "https://www.seznamzpravy.cz/clanek/kultura-ratolesti-serial-recenze-288191",
      "picture": "https://encrypted-tbn3.gstatic.com/images?q=tbn:ANd9GcT_qLWryuikO2eNebNTejfsljB0yF9Uro_7JR4D7CaL7QlJX5PDsOFPYulW98o",
      "traffic": "500++ hledání",
      "source": "Seznam Zprávy",
      "explore_url": "https://trends.google.cz/trends/explore?q=ratolesti serial&geo=CZ"
    },
    {
      "rank": 3,
      "query": "celta vigo – atlético madrid",
      "news_title": "Atletico Madrid vs Celta: Předpokládaná sestava",
      "news_url": "https://sports.yahoo.com/article/atletico-madrid-xi-vs-celta-051000811.html",
      "picture": "https://encrypted-tbn1.gstatic.com/images?q=tbn:ANd9GcRaA4idDkhHC44xptzx5hNrHjUksOBoQ-y7ifbuYSjKxpW2RSc8oaNx9M-V4G4",
      "traffic": "200++ hledání",
      "source": "Yahoo Sports",
      "explore_url": "https://trends.google.cz/trends/explore?q=celta vigo – atlético madrid&geo=CZ"
    },
    {
      "rank": 4,
      "query": "o2 arena",
      "news_title": "Areny pro začínající umělce: dobrý krok?",
      "news_url": "https://faroutmagazine.co.uk/the-rise-in-artists-hitting-arenas-should-they/",
      "picture": "https://encrypted-tbn0.gstatic.com/images?q=tbn:ANd9GcTEdwwjpwpBtdKNHgEdwvVCSptNQk5ulUIs2HYVokOPZjEo2limKSo7qvEdjqY",
      "traffic": "200++ hledání",
      "source": "Far Out Magazine",
      "explore_url": "https://trends.google.cz/trends/explore?q=o2 arena&geo=CZ"
    },
    {
      "rank": 5,
      "query": "ted bundy",
      "news_title": "Monstrum: Ted Bundy v úvodní epizodě nové série",
      "news_url": "https://www.al.com/tv/2025/10/mind-of-a-monster-tackles-infamous-serial-killer-ted-bundy-during-season-1-premiere.html",
      "picture": "https://encrypted-tbn2.gstatic.com/images?q=tbn:ANd9GcRK9CYjEB6qoh-PAmTTVAIxFHgbSpPFijzwcXOoMtanu-kmTllOGX8za320hU0",
      "traffic": "100++ hledání",
      "source": "AL.com",
      "explore_url": "https://trends.google.cz/trends/explore?q=ted bundy&geo=CZ"
    },
    {
      "rank": 6,
      "query": "adeline watkins",
      "news_title": "Skutečná Adeline Watkinsová randila s Edem Geinem? Pravdivý příběh role Suzanny Son",
      "news_url": "https://www.marieclaire.com/culture/tv-shows/who-was-adeline-watkins-monster-the-ed-gein-story/",
      "picture": "https://encrypted-tbn0.gstatic.com/images?q=tbn:ANd9GcQ1e0isyoubGaRhWFHPKuXrVGjs10FcNO09GPj2zgygJfCqEIfW4q32UyuY9-4",
      "traffic": "100++ hledání",
      "source": "Marie Claire",
      "explore_url": "https://trends.google.cz/trends/explore?q=adeline watkins&geo=CZ"
    },
    {
      "rank": 7,
      "query": "zuzana majerová",
      "news_title": "Nové tváře Sněmovny: Turek, Ševčík, Šichtařová, Svárovská",
      "news_url": "https://www.seznamzpravy.cz/clanek/volby-do-poslanecke-snemovny-nove-tvare-snemovny-turek-sevcik-sichtarova-nebo-zelena-svarovska-288013",
      "picture": "https://encrypted-tbn3.gstatic.com/images?q=tbn:ANd9GcQGCHXUbXRo7nqJqxt8m0IlX1WMW6adfM2Yi5FULGI_vV2KjeMQ8iPe70trWSs",
      "traffic": "100++ hledání",
      "source": "Seznam Zprávy",
      "explore_url": "https://trends.google.cz/trends/explore?q=zuzana majerová&geo=CZ"
    },
    {
      "rank": 8,
      "query": "ilse koch",
      "news_title": "Děsivý pravdivý příběh seriálu Monster: Příběh Eda Geina",
      "news_url": "https://time.com/7322672/ed-gein-true-story-monster-ryan-murphy/",
      "picture": "https://encrypted-tbn0.gstatic.com/images?q=tbn:ANd9GcQZAdi-7mGmmDtwnkSIIl_rBopJwjaG3Sp1Yzq73iBL6i7mJcCTjqmnK96Saks",
      "traffic": "100++ hledání",
      "source": "Time Magazine",
      "explore_url": "https://trends.google.cz/trends/explore?q=ilse koch&geo=CZ"
    }
  ]
}